cyberfusion/WorkItemAutomations/__init__.py
cyberfusion/WorkItemAutomations/cli.py
cyberfusion/WorkItemAutomations/config.py
cyberfusion/WorkItemAutomations/gitlab.py
cyberfusion/WorkItemAutomations/automations/__init__.py
cyberfusion/WorkItemAutomations/automations/base.py
cyberfusion/WorkItemAutomations/automations/create_issue.py
cyberfusion/WorkItemAutomations/automations/nop.py
cyberfusion/WorkItemAutomations/automations/summarise_issues.py
python3_cyberfusion_work_item_automations-1.6.dist-info/METADATA
python3_cyberfusion_work_item_automations-1.6.dist-info/WHEEL
python3_cyberfusion_work_item_automations-1.6.dist-info/entry_points.txt
python3_cyberfusion_work_item_automations-1.6.dist-info/top_level.txt
python3_cyberfusion_work_item_automations-1.6.dist-info/RECORD
