Metadata-Version: 2.4
Name: python3-cyberfusion-work-item-automations
Version: 1.6
Summary: Automations for GitLab work items.
Author-email: Cyberfusion <support@cyberfusion.io>
Project-URL: Source, https://github.com/CyberfusionIO/python3-cyberfusion-work-item-automations
Requires-Dist: PyYAML==6.0.2
Requires-Dist: python-gitlab==4.9.0
Requires-Dist: docopt==0.6.2
Requires-Dist: schema==0.7.7
Requires-Dist: croniter==2.0.7
Requires-Dist: tabulate==0.9.0
